{
  "project_info": {
    "project_number": "846846679406",
    "firebase_url": "https://pace-arcadian.firebaseio.com",
    "project_id": "pace-arcadian",
    "storage_bucket": "pace-arcadian.appspot.com"
  },
  "client": [
    {
      "client_info": {
        "mobilesdk_app_id": "1:846846679406:android:83b79c4ce34efd5d",
        "android_client_info": {
          "package_name": "com.example.pacearcadian"
        }
      },
      "oauth_client": [
        {
          "client_id": "846846679406-f6lmvftesem4mujvg2i6jq2fug63jjtt.apps.googleusercontent.com",
          "client_type": 1,
          "android_info": {
            "package_name": "com.example.pacearcadian",
            "certificate_hash": "ee6460040a6a98267bd8b9f9a7849623c22d2c7f"
          }
        },
        {
          "client_id": "846846679406-t0pp7m79l8ar0tt1070tpno7tiupfob8.apps.googleusercontent.com",
          "client_type": 3
        }
      ],
      "api_key": [
        {
          "current_key": "AIzaSyBDpbofTBgNdJIUR_hR1hFSrGJqo4YlJhw"
        }
      ],
      "services": {
        "appinvite_service": {
          "other_platform_oauth_client": [
            {
              "client_id": "846846679406-t0pp7m79l8ar0tt1070tpno7tiupfob8.apps.googleusercontent.com",
              "client_type": 3
            }
          ]
        }
      }
    }
  ],
  "configuration_version": "1"
}